phaneron/__init__.py
phaneron/camera_path_handler.py
phaneron/circuit_explorer.py
phaneron/diffuse_tensor_imaging.py
phaneron/graph_explorer.py
phaneron/steps.py
phaneron/version.py
phaneron-0.1.7.dist-info/METADATA
phaneron-0.1.7.dist-info/RECORD
phaneron-0.1.7.dist-info/WHEEL
phaneron-0.1.7.dist-info/top_level.txt
