Metadata-Version: 2.1
Name: phaneron
Version: 0.1.7
Summary: Helper function for Phaneron
Home-page: https://github.com/favreau/pyPhaneron.git
Author: Cyrille Favreau
Author-email: cyrille.favreau@gmail.com
License: GNU LGPL
Platform: UNKNOWN
Requires-Dist: brayns (~=0.8.0)
Requires-Dist: matplotlib (~=2.1.2)
Requires-Dist: scipy (~=0.19.1)
Requires-Dist: numpy (~=1.14.5)
Requires-Dist: seaborn (~=0.8.1)
